IPP/Image_Inference.py
IPP/Image_Postprocessor.py
IPP/Image_Preprocessor.py
IPP/__init__.py
IPP/convert.py
IPP/model.py
IPP/test.py
image_processor_perfios-0.2.3.dist-info/METADATA
image_processor_perfios-0.2.3.dist-info/WHEEL
image_processor_perfios-0.2.3.dist-info/top_level.txt
image_processor_perfios-0.2.3.dist-info/RECORD
